matn/__init__.py
matn/cli.py
matn/counters.py
matn/elements.py
matn/helpers.py
matn/normalizers.py
matn/special_articles.py
matn-0.2.2.dist-info/LICENSE
matn-0.2.2.dist-info/METADATA
matn-0.2.2.dist-info/WHEEL
matn-0.2.2.dist-info/entry_points.txt
matn-0.2.2.dist-info/top_level.txt
matn-0.2.2.dist-info/RECORD
