Metadata-Version: 2.1
Name: matn
Version: 0.2.2
Summary: Arabic text processor tool.
Home-page: https://github.com/iamjazzar/matn
Author: Ahmed Jazzar
Author-email: me@ahmedjazzar.com
License: MIT License
Classifier: Development Status :: 5 - Production/Stable
Classifier: Intended Audience :: Developers
Classifier: Operating System :: OS Independent
Classifier: Programming Language :: Python :: 3
Classifier: Programming Language :: Python :: 3.7
Classifier: Programming Language :: Python :: 3.8
Classifier: Programming Language :: Python :: 3.9
Classifier: Programming Language :: Python :: 3.10
Classifier: License :: OSI Approved :: MIT License
Classifier: Topic :: Software Development
License-File: LICENSE
